track_history/__init__.py
track_history/decorators.py
track_history/handlers.py
track_history/manager.py
track_history/middleware.py
track_history/models.py
track_history/query.py
track_history/settings.py
track_history/tracker.py
track_history/utils.py
track_history/migrations/0001_initial.py
track_history/migrations/0002_auto_20200524_1009.py
track_history/migrations/0003_replace_jsonfield.py
track_history/migrations/__init__.py
django_track_history-0.2.2.dist-info/LICENSE
django_track_history-0.2.2.dist-info/METADATA
django_track_history-0.2.2.dist-info/WHEEL
django_track_history-0.2.2.dist-info/top_level.txt
django_track_history-0.2.2.dist-info/RECORD
